asgi_request_logger/__init__.py
asgi_request_logger/json_request_logger_middleware.py
asgi_request_logger/logger.py
asgi_request_logger-0.3.2.dist-info/LICENSE
asgi_request_logger-0.3.2.dist-info/METADATA
asgi_request_logger-0.3.2.dist-info/WHEEL
asgi_request_logger-0.3.2.dist-info/RECORD
