Metadata-Version: 2.3
Name: asgi-request-logger
Version: 0.3.2
Summary: A lightweight request logger middleware for ASGI applications
License: MIT
Author: timothy jeong
Author-email: k.jts8257@gmail.com
Requires-Python: >=3.9,<4.0
Classifier: License :: OSI Approved :: MIT License
Classifier: Programming Language :: Python :: 3
Classifier: Programming Language :: Python :: 3.9
Classifier: Programming Language :: Python :: 3.10
Classifier: Programming Language :: Python :: 3.11
Classifier: Programming Language :: Python :: 3.12
Classifier: Programming Language :: Python :: 3.13
Requires-Dist: asgiref (>=3.6.0,<4.0.0)
Project-URL: Homepage, https://github.com/timothy-jeong/asgi-request-logger
Project-URL: Repository, https://github.com/timothy-jeong/asgi-request-logger
